taskdetailsextractor/__init__.py
taskdetailsextractor/task_details_extractor.py
taskdetailsextractor-2025.5.180918.dist-info/licenses/LICENSE
tests/__init__.py
taskdetailsextractor-2025.5.180918.dist-info/METADATA
taskdetailsextractor-2025.5.180918.dist-info/WHEEL
taskdetailsextractor-2025.5.180918.dist-info/top_level.txt
taskdetailsextractor-2025.5.180918.dist-info/RECORD
