Metadata-Version: 2.4
Name: TaskDetailsExtractor
Version: 2025.5.180918
Summary: Extract detailed tasks for software project modification using GPT from OpenAI.
Home-page: https://github.com/chigwell/TaskDetailsExtractor
Author: Eugene Evstafev
Author-email: chigwel@gmail.com
Classifier: Programming Language :: Python :: 3
Classifier: License :: OSI Approved :: MIT License
Classifier: Operating System :: OS Independent
Requires-Python: >=3.6
License-File: LICENSE
Requires-Dist: openai
Requires-Dist: projectstructor>=0.0.1
Dynamic: author
Dynamic: author-email
Dynamic: classifier
Dynamic: description
Dynamic: description-content-type
Dynamic: home-page
Dynamic: license-file
Dynamic: requires-dist
Dynamic: requires-python
Dynamic: summary
